{
  "allow_mixed_adjustments": false,
  "benchmark_definitions": {
    "capital": 100000,
    "execution_timing": "next_open",
    "symbol": "STABLE",
    "type": "single_symbol_buy_and_hold"
  },
  "constraint_parameters": {
    "cash_buffer": 0.01,
    "max_gross_exposure": 1.0,
    "max_single_weight": 1.0
  },
  "constructor_parameters": {},
  "cost_analysis": {},
  "data_alignment_mode": "union",
  "data_manifest": "tests/fixtures/sit_snapshot/manifest.json",
  "data_root": "tests/fixtures/sit_snapshot",
  "diagnostic_only": false,
  "end_date": "2024-02-08",
  "execution_parameters": {
    "execution_timing": "next_open",
    "lot_size": 100
  },
  "experiment_mode": "fixed_selection",
  "experiment_name": "sit-schema-2-synthetic-fixed-selection",
  "fee_parameters": {
    "commission_rate": 0.001,
    "minimum_commission": 2.0
  },
  "initial_cash": 100000,
  "notes": "Deterministic synthetic integration fixture; no investment-performance claim",
  "output_directory": "results/sit-synthetic-fixed",
  "parameter_selection": {
    "failure_policy": "continue",
    "minimum_observations": 2,
    "objective_direction": "maximize",
    "parameter_constraints": [],
    "parameter_grid": {
      "top_k": [
        1,
        2
      ]
    },
    "selection_objective": "total_return",
    "tie_break_rules": [
      "canonical_parameters"
    ]
  },
  "portfolio_constructor": "strategy-native",
  "random_seed": 42,
  "resource_limits": {
    "execution": "serial",
    "maximum_candidate_count": 2
  },
  "schema_version": "2.0",
  "slippage_parameters": {
    "slippage_rate": 0.001
  },
  "split_definitions": {
    "test_end": "2024-02-08",
    "test_start": "2024-02-02",
    "train_end": "2024-01-26",
    "train_start": "2024-01-24",
    "type": "fixed",
    "validation_end": "2024-02-01",
    "validation_start": "2024-01-29",
    "warmup_observations": 3
  },
  "start_date": "2024-01-24",
  "strategy_class": "SITMomentumRotationStrategy",
  "strategy_parameters": {
    "max_weight": 0.8,
    "minimum_listing_age": 4,
    "momentum_lookback": 3,
    "rebalance_frequency": "interval",
    "rebalance_interval": 3,
    "top_k": 2,
    "trend_window": 3,
    "volatility_lookback": 3
  },
  "universe": [
    "STABLE",
    "VOLATILE",
    "LATE"
  ],
  "warmup_policy": "history_only"
}
